restpipe-0.2.11.data/scripts/rp_client_set_identity
restpipe-0.2.11.data/scripts/rp_client_start_gunicorn_dev
restpipe-0.2.11.data/scripts/rp_client_start_gunicorn_prod
restpipe-0.2.11.data/scripts/rp_server_set_identity
restpipe-0.2.11.data/scripts/rp_server_start_gunicorn_dev
restpipe-0.2.11.data/scripts/rp_server_start_gunicorn_prod
restpipe-0.2.11.dist-info/DESCRIPTION.rst
restpipe-0.2.11.dist-info/METADATA
restpipe-0.2.11.dist-info/metadata.json
restpipe-0.2.11.dist-info/RECORD
restpipe-0.2.11.dist-info/top_level.txt
restpipe-0.2.11.dist-info/WHEEL
rpipe/__init__.py
rpipe/__init__.pyc
rpipe/connection.py
rpipe/event.py
rpipe/event_response.py
rpipe/exceptions.py
rpipe/message_exchange.py
rpipe/message_loop.py
rpipe/protocol.py
rpipe/request_server.py
rpipe/state_change_event.py
rpipe/stats.py
rpipe/utility.py
rpipe/app/__init__.py
rpipe/app/client.py
rpipe/app/server.py
rpipe/app/wsgi_client.py
rpipe/app/wsgi_server.py
rpipe/client/__init__.py
rpipe/client/connection.py
rpipe/config/__init__.py
rpipe/config/client.py
rpipe/config/client_web.py
rpipe/config/exchange.py
rpipe/config/general.py
rpipe/config/log.py
rpipe/config/protocol.py
rpipe/config/server.py
rpipe/config/server_web.py
rpipe/config/statsd.py
rpipe/config/web_server.py
rpipe/protocols/__init__.py
rpipe/protocols/event_pb2.py
rpipe/protocols/heartbeat_pb2.py
rpipe/resources/README.rst
rpipe/resources/requirements.txt
rpipe/resources/data/gunicorn_conf_client_dev.py
rpipe/resources/data/gunicorn_conf_client_prod.py
rpipe/resources/data/gunicorn_conf_server_dev.py
rpipe/resources/data/gunicorn_conf_server_prod.py
rpipe/resources/protobuf/build.sh
rpipe/resources/protobuf/event.proto
rpipe/resources/protobuf/heartbeat.proto
rpipe/resources/scripts/rp_client_set_identity
rpipe/resources/scripts/rp_client_start_gunicorn_dev
rpipe/resources/scripts/rp_client_start_gunicorn_prod
rpipe/resources/scripts/rp_server_set_identity
rpipe/resources/scripts/rp_server_start_gunicorn_dev
rpipe/resources/scripts/rp_server_start_gunicorn_prod
rpipe/resources/ssl/.git
rpipe/resources/ssl/.gitignore
rpipe/resources/ssl/create.py
rpipe/resources/ssl/create_ca.py
