Metadata-Version: 2.0
Name: restpipe
Version: 0.2.11
Summary: An SSL-authenticated, durable, bidirectional, RESTful, client-server pipe that transports custom events.
Home-page: https://github.com/dsoprea/RestPipe
Author: Dustin Oprea
Author-email: myselfasunder@gmail.com
License: GPL 2
Keywords: gevent ssl socket rest event
Platform: UNKNOWN
Requires-Dist: M2Crypto (==0.22.3)
Requires-Dist: gevent (==1.0.1)
Requires-Dist: greenlet (==0.4.2)
Requires-Dist: gunicorn
Requires-Dist: protobuf (==2.5.0)
Requires-Dist: statsd (==3.0)
Requires-Dist: web.py (==0.37)
Requires-Dist: wsgiref (==0.1.2)
